{
  "memory_id": "L1-2026-04-06-001",
  "level": "L1",
  "created": "2026-04-06",
  "sources": {
    "sessionIds": [
      "5b2ed1d3",
      "ce4f584d",
      "d0c8f707",
      "e0b0d67c",
      "7fa51c49",
      "3a7ab05a",
      "39d15e5b",
      "df0f198e",
      "d6f7c781",
      "a98ff5fd",
      "99d6c6e1",
      "fd554545",
      "c5a4af61",
      "100a47e6",
      "7aa317cb",
      "1fe4d07a",
      "db699555",
      "60261f52",
      "6688c32b",
      "64b9ad15",
      "2b1d94fb",
      "a3b68c8f",
      "effa6572",
      "433a589a",
      "f27680fa",
      "ac49caa4",
      "ead407de",
      "932e7c26",
      "387e6d1c",
      "48f79f36",
      "9ddf4323",
      "4d79daf4",
      "01fcb056",
      "2cba8301",
      "2620b1e5",
      "bd317484",
      "8bc3d467",
      "f184ea08",
      "a7b2e648"
    ],
    "timestampRange": {
      "start": "2026-04-06T01:00:00.127Z",
      "end": "2026-04-06T15:01:43.828Z"
    },
    "messageCount": 39
  }
}